MANIFEST.in
README.rst
setup.py
./cycloudpickle/cycloudpickle.c
./cycloudpickle/cypickle.c
cycloudpickle/__init__.py
cycloudpickle/cycloudpickle.c
cycloudpickle/cycloudpickle.pyx
cycloudpickle/cypickle.c
cycloudpickle/cypickle.pxd
cycloudpickle/cypickle.pyx
cycloudpickle.egg-info/PKG-INFO
cycloudpickle.egg-info/SOURCES.txt
cycloudpickle.egg-info/dependency_links.txt
cycloudpickle.egg-info/not-zip-safe
cycloudpickle.egg-info/requires.txt
cycloudpickle.egg-info/top_level.txt
tests/__init__.py
tests/cloudpickle_file_test.py
tests/cloudpickle_test.py
tests/testutils.py