Metadata-Version: 1.1
Name: cycloudpickle
Version: 0.1.0
Summary: A cython version of cloudpickle
Home-page: https://github.com/bndl/cycloudpickle
Author: Frens Jan Rumph
Author-email: mail@frensjan.nl
License: UNKNOWN
Platform: UNKNOWN
Classifier: Development Status :: 4 - Beta
Classifier: Intended Audience :: Developers
Classifier: Operating System :: OS Independent
Classifier: Programming Language :: Python
Classifier: Programming Language :: Python :: 3.4
Classifier: Programming Language :: Python :: 3.5
Classifier: Programming Language :: Python :: 3.6
